outlierRemoval_python/outlierRemoval.py
outlierRemoval_kvarshney_101703295-1.0.3.dist-info/LICENSE
outlierRemoval_kvarshney_101703295-1.0.3.dist-info/METADATA
outlierRemoval_kvarshney_101703295-1.0.3.dist-info/WHEEL
outlierRemoval_kvarshney_101703295-1.0.3.dist-info/entry_points.txt
outlierRemoval_kvarshney_101703295-1.0.3.dist-info/top_level.txt
outlierRemoval_kvarshney_101703295-1.0.3.dist-info/RECORD
